paxy/__init__.py
paxy/cli.py
paxy/commands/__init__.py
paxy/commands/base.py
paxy/commands/core/__init__.py
paxy/commands/core/compare.py
paxy/commands/core/convert.py
paxy/commands/core/dec.py
paxy/commands/core/gosub.py
paxy/commands/core/ifjump.py
paxy/commands/core/igl.py
paxy/commands/core/importer.py
paxy/commands/core/inc.py
paxy/commands/core/inop.py
paxy/commands/core/inp.py
paxy/commands/core/isbop.py
paxy/commands/core/label.py
paxy/commands/core/let.py
paxy/commands/core/mad.py
paxy/commands/core/map.py
paxy/commands/core/mapdel.py
paxy/commands/core/par.py
paxy/commands/core/pnt.py
paxy/commands/core/returnstmt.py
paxy/commands/core/row.py
paxy/commands/core/vec.py
paxy/commands/data/__init__.py
paxy/commands/std/__init__.py
paxy/commands/std/files.py
paxy/commands/std/formats.py
paxy/commands/std/maths.py
paxy/commands/std/text.py
paxy/commands/std/time.py
paxy/commands/ui/__init__.py
paxy/commands/web/__init__.py
paxy/compiler/__init__.py
paxy/compiler/assembler.py
paxy/compiler/debug.py
paxy/compiler/ir.py
paxy/compiler/opcoerce.py
paxy/compiler/parser.py
paxy/compiler/twelve.py
paxy-0.3.0.dist-info/METADATA
paxy-0.3.0.dist-info/WHEEL
paxy-0.3.0.dist-info/entry_points.txt
paxy-0.3.0.dist-info/top_level.txt
paxy-0.3.0.dist-info/RECORD
