Metadata-Version: 2.4
Name: paxy
Version: 0.3.0
Summary: Paxy: a modern BASIC-like language that compiles to Python bytecode (.pyc).
Author-email: Zeth Green <theology@gmail.com>
License-Expression: MIT
Project-URL: Homepage, https://github.com/zeth/paxy
Project-URL: Documentation, https://github.com/zeth/paxy#readme
Project-URL: Repository, https://github.com/zeth/paxy
Project-URL: Issues, https://github.com/zeth/paxy/issues
Classifier: Development Status :: 3 - Alpha
Classifier: Intended Audience :: Education
Classifier: Intended Audience :: Developers
Classifier: Programming Language :: Python
Classifier: Programming Language :: Python :: 3.12
Classifier: Programming Language :: Python :: 3.13
Classifier: Programming Language :: Python :: 3.14
Classifier: Topic :: Software Development :: Compilers
Classifier: Topic :: Education
Classifier: Topic :: Utilities
Requires-Python: >=3.12
Requires-Dist: bytecode>=0.17.0
Provides-Extra: dev
Requires-Dist: pytest>=7.0; extra == "dev"
Requires-Dist: sphinx; extra == "dev"
Requires-Dist: myst-parser; extra == "dev"
